Workbook
Name CompanyName: Invoice!$B$1
Name CustomerLookup: #REF!
Name Invoice_No: #REF!
Name InvoiceNoDetails: "InvoiceDetails[Invoice No]"
Name rngInvoice: Invoice!$G$6

Sheet Invoice
B1: Kumar Coaters
B3: ="Invoice for: "&IFERROR(VLOOKUP(rngInvoice,#REF!,4),"") -> Invoice for:
B4: Address: | C4: Gat No.123, Near Sadguru Market, Murhe Wasti, Moi Road, | D4: Phone: | E4: ************ | F4: Email: | G4: ********************
C5: Kuruli, Chakan, Pune -410501 | D5: Fax: | E5: ************ | F5: Website: | G5: https://kumarcoaters.com/
B6: Bill To: | C6: ********* | D6: Phone: | E6: ***************** | F6: Invoice #: | G6: 3-456-2
C7: ************ | D7: Fax: | E7: ****************** | F7: Invoice Date:
C8: ************* | D8: Email: | E8: **************************
B10: Item # | C10: Description | D10: Qty | E10: Unit Price | F10: Discount | G10: Price
B11: {=IFERROR(INDEX(InvoiceDetails[],SMALL(IF(InvoiceDetails[Invoice '#]=rngInvoice,ROW(InvoiceDetails[])-ROW(InvoiceDetails[#Headers])), ROW(1:1)), MATCH($B$10, InvoiceDetails[#Headers], 0)),"")} -> PC-IND-ES58E-77 | C11: {=IFERROR(INDEX(InvoiceDetails[],SMALL(IF(InvoiceDetails[Invoice '#]=rngInvoice,ROW(InvoiceDetails[])-ROW(InvoiceDetails[#Headers])), ROW(1:1)), MATCH($C$10, InvoiceDetails[#Headers], 0)),"")} -> INV-2301-002 | D11: {=IFERROR(INDEX(InvoiceDetails[],SMALL(IF(InvoiceDetails[Invoice '#]=rngInvoice,ROW(InvoiceDetails[])-ROW(InvoiceDetails[#Headers])), ROW(1:1)), MATCH($D$10, InvoiceDetails[#Headers], 0)),"")} -> 717 | E11: {=IFERROR(INDEX(InvoiceDetails[],SMALL(IF(InvoiceDetails[Invoice '#]=rngInvoice,ROW(InvoiceDetails[])-ROW(InvoiceDetails[#Headers])), ROW(1:1)), MATCH($E$10, InvoiceDetails[#Headers], 0)),"")} -> 30 | F11: {=IFERROR(INDEX(InvoiceDetails[],SMALL(IF(InvoiceDetails[Invoice '#]=rngInvoice,ROW(InvoiceDetails[])-ROW(InvoiceDetails[#Headers])), ROW(1:1)), MATCH($F$10, InvoiceDetails[#Headers], 0)),"")} -> 2 | G11: =IFERROR((D11*E11)-F11,"") -> 21508
B12: {=IFERROR(INDEX(InvoiceDetails[],SMALL(IF(InvoiceDetails[Invoice '#]=rngInvoice,ROW(InvoiceDetails[])-ROW(InvoiceDetails[#Headers])), ROW(4:4)), MATCH($B$10, InvoiceDetails[#Headers], 0)),"")} -> ED-IND-BU40X-81 | C12: {=IFERROR(INDEX(InvoiceDetails[],SMALL(IF(InvoiceDetails[Invoice '#]=rngInvoice,ROW(InvoiceDetails[])-ROW(InvoiceDetails[#Headers])), ROW(4:4)), MATCH($C$10, InvoiceDetails[#Headers], 0)),"")} -> INV-2301-028 | D12: {=IFERROR(INDEX(InvoiceDetails[],SMALL(IF(InvoiceDetails[Invoice '#]=rngInvoice,ROW(InvoiceDetails[])-ROW(InvoiceDetails[#Headers])), ROW(4:4)), MATCH($D$10, InvoiceDetails[#Headers], 0)),"")} -> 800 | E12: {=IFERROR(INDEX(InvoiceDetails[],SMALL(IF(InvoiceDetails[Invoice '#]=rngInvoice,ROW(InvoiceDetails[])-ROW(InvoiceDetails[#Headers])), ROW(4:4)), MATCH($E$10, InvoiceDetails[#Headers], 0)),"")} -> 31 | F12: {=IFERROR(INDEX(InvoiceDetails[],SMALL(IF(InvoiceDetails[Invoice '#]=rngInvoice,ROW(InvoiceDetails[])-ROW(InvoiceDetails[#Headers])), ROW(4:4)), MATCH($F$10, InvoiceDetails[#Headers], 0)),"")} -> 7 | G12: =IFERROR((D12*E12)-F12,"") -> 24793
B13: {=IFERROR(INDEX(InvoiceDetails[],SMALL(IF(InvoiceDetails[Invoice '#]=rngInvoice,ROW(InvoiceDetails[])-ROW(InvoiceDetails[#Headers])), ROW(5:5)), MATCH($B$10, InvoiceDetails[#Headers], 0)),"")} -> ED-IND-TV20R-31 | C13: {=IFERROR(INDEX(InvoiceDetails[],SMALL(IF(InvoiceDetails[Invoice '#]=rngInvoice,ROW(InvoiceDetails[])-ROW(InvoiceDetails[#Headers])), ROW(5:5)), MATCH($C$10, InvoiceDetails[#Headers], 0)),"")} -> INV-2302-029 | D13: {=IFERROR(INDEX(InvoiceDetails[],SMALL(IF(InvoiceDetails[Invoice '#]=rngInvoice,ROW(InvoiceDetails[])-ROW(InvoiceDetails[#Headers])), ROW(5:5)), MATCH($D$10, InvoiceDetails[#Headers], 0)),"")} -> 994 | E13: {=IFERROR(INDEX(InvoiceDetails[],SMALL(IF(InvoiceDetails[Invoice '#]=rngInvoice,ROW(InvoiceDetails[])-ROW(InvoiceDetails[#Headers])), ROW(5:5)), MATCH($E$10, InvoiceDetails[#Headers], 0)),"")} -> 21 | F13: {=IFERROR(INDEX(InvoiceDetails[],SMALL(IF(InvoiceDetails[Invoice '#]=rngInvoice,ROW(InvoiceDetails[])-ROW(InvoiceDetails[#Headers])), ROW(5:5)), MATCH($F$10, InvoiceDetails[#Headers], 0)),"")} -> 0 | G13: =IFERROR((D13*E13)-F13,"") -> 20874
B14: {=IFERROR(INDEX(InvoiceDetails[],SMALL(IF(InvoiceDetails[Invoice '#]=rngInvoice,ROW(InvoiceDetails[])-ROW(InvoiceDetails[#Headers])), ROW(6:6)), MATCH($B$10, InvoiceDetails[#Headers], 0)),"")} -> ED-IND-UU36L-66 | C14: {=IFERROR(INDEX(InvoiceDetails[],SMALL(IF(InvoiceDetails[Invoice '#]=rngInvoice,ROW(InvoiceDetails[])-ROW(InvoiceDetails[#Headers])), ROW(6:6)), MATCH($C$10, InvoiceDetails[#Headers], 0)),"")} -> INV-2302-030 | D14: {=IFERROR(INDEX(InvoiceDetails[],SMALL(IF(InvoiceDetails[Invoice '#]=rngInvoice,ROW(InvoiceDetails[])-ROW(InvoiceDetails[#Headers])), ROW(6:6)), MATCH($D$10, InvoiceDetails[#Headers], 0)),"")} -> 533 | E14: {=IFERROR(INDEX(InvoiceDetails[],SMALL(IF(InvoiceDetails[Invoice '#]=rngInvoice,ROW(InvoiceDetails[])-ROW(InvoiceDetails[#Headers])), ROW(6:6)), MATCH($E$10, InvoiceDetails[#Headers], 0)),"")} -> 26 | F14: {=IFERROR(INDEX(InvoiceDetails[],SMALL(IF(InvoiceDetails[Invoice '#]=rngInvoice,ROW(InvoiceDetails[])-ROW(InvoiceDetails[#Headers])), ROW(6:6)), MATCH($F$10, InvoiceDetails[#Headers], 0)),"")} -> 0 | G14: =IFERROR((D14*E14)-F14,"") -> 13858
B15: {=IFERROR(INDEX(InvoiceDetails[],SMALL(IF(InvoiceDetails[Invoice '#]=rngInvoice,ROW(InvoiceDetails[])-ROW(InvoiceDetails[#Headers])), ROW(7:7)), MATCH($B$10, InvoiceDetails[#Headers], 0)),"")} -> ED-IND-FE78W-05 | C15: {=IFERROR(INDEX(InvoiceDetails[],SMALL(IF(InvoiceDetails[Invoice '#]=rngInvoice,ROW(InvoiceDetails[])-ROW(InvoiceDetails[#Headers])), ROW(7:7)), MATCH($C$10, InvoiceDetails[#Headers], 0)),"")} -> INV-2302-031 | D15: {=IFERROR(INDEX(InvoiceDetails[],SMALL(IF(InvoiceDetails[Invoice '#]=rngInvoice,ROW(InvoiceDetails[])-ROW(InvoiceDetails[#Headers])), ROW(7:7)), MATCH($D$10, InvoiceDetails[#Headers], 0)),"")} -> 998 | E15: {=IFERROR(INDEX(InvoiceDetails[],SMALL(IF(InvoiceDetails[Invoice '#]=rngInvoice,ROW(InvoiceDetails[])-ROW(InvoiceDetails[#Headers])), ROW(7:7)), MATCH($E$10, InvoiceDetails[#Headers], 0)),"")} -> 29 | F15: {=IFERROR(INDEX(InvoiceDetails[],SMALL(IF(InvoiceDetails[Invoice '#]=rngInvoice,ROW(InvoiceDetails[])-ROW(InvoiceDetails[#Headers])), ROW(7:7)), MATCH($F$10, InvoiceDetails[#Headers], 0)),"")} -> 0 | G15: =IFERROR((D15*E15)-F15,"") -> 28942
B16: {=IFERROR(INDEX(InvoiceDetails[],SMALL(IF(InvoiceDetails[Invoice '#]=rngInvoice,ROW(InvoiceDetails[])-ROW(InvoiceDetails[#Headers])), ROW(8:8)), MATCH($B$10, InvoiceDetails[#Headers], 0)),"")} -> ED-IND-KQ16R-25 | C16: {=IFERROR(INDEX(InvoiceDetails[],SMALL(IF(InvoiceDetails[Invoice '#]=rngInvoice,ROW(InvoiceDetails[])-ROW(InvoiceDetails[#Headers])), ROW(8:8)), MATCH($C$10, InvoiceDetails[#Headers], 0)),"")} -> INV-2302-032 | D16: {=IFERROR(INDEX(InvoiceDetails[],SMALL(IF(InvoiceDetails[Invoice '#]=rngInvoice,ROW(InvoiceDetails[])-ROW(InvoiceDetails[#Headers])), ROW(8:8)), MATCH($D$10, InvoiceDetails[#Headers], 0)),"")} -> 851 | E16: {=IFERROR(INDEX(InvoiceDetails[],SMALL(IF(InvoiceDetails[Invoice '#]=rngInvoice,ROW(InvoiceDetails[])-ROW(InvoiceDetails[#Headers])), ROW(8:8)), MATCH($E$10, InvoiceDetails[#Headers], 0)),"")} -> 24 | F16: {=IFERROR(INDEX(InvoiceDetails[],SMALL(IF(InvoiceDetails[Invoice '#]=rngInvoice,ROW(InvoiceDetails[])-ROW(InvoiceDetails[#Headers])), ROW(8:8)), MATCH($F$10, InvoiceDetails[#Headers], 0)),"")} -> 0 | G16: =IFERROR((D16*E16)-F16,"") -> 20424
B17: {=IFERROR(INDEX(InvoiceDetails[],SMALL(IF(InvoiceDetails[Invoice '#]=rngInvoice,ROW(InvoiceDetails[])-ROW(InvoiceDetails[#Headers])), ROW(9:9)), MATCH($B$10, InvoiceDetails[#Headers], 0)),"")} -> ED-IND-JK94K-77 | C17: {=IFERROR(INDEX(InvoiceDetails[],SMALL(IF(InvoiceDetails[Invoice '#]=rngInvoice,ROW(InvoiceDetails[])-ROW(InvoiceDetails[#Headers])), ROW(9:9)), MATCH($C$10, InvoiceDetails[#Headers], 0)),"")} -> INV-2302-033 | D17: {=IFERROR(INDEX(InvoiceDetails[],SMALL(IF(InvoiceDetails[Invoice '#]=rngInvoice,ROW(InvoiceDetails[])-ROW(InvoiceDetails[#Headers])), ROW(9:9)), MATCH($D$10, InvoiceDetails[#Headers], 0)),"")} -> 919 | E17: {=IFERROR(INDEX(InvoiceDetails[],SMALL(IF(InvoiceDetails[Invoice '#]=rngInvoice,ROW(InvoiceDetails[])-ROW(InvoiceDetails[#Headers])), ROW(9:9)), MATCH($E$10, InvoiceDetails[#Headers], 0)),"")} -> 21 | F17: {=IFERROR(INDEX(InvoiceDetails[],SMALL(IF(InvoiceDetails[Invoice '#]=rngInvoice,ROW(InvoiceDetails[])-ROW(InvoiceDetails[#Headers])), ROW(9:9)), MATCH($F$10, InvoiceDetails[#Headers], 0)),"")} -> 0 | G17: =IFERROR((D17*E17)-F17,"") -> 19299
B18: {=IFERROR(INDEX(InvoiceDetails[],SMALL(IF(InvoiceDetails[Invoice '#]=rngInvoice,ROW(InvoiceDetails[])-ROW(InvoiceDetails[#Headers])), ROW(10:10)), MATCH($B$10, InvoiceDetails[#Headers], 0)),"")} -> ED-IND-CR92V-20 | C18: {=IFERROR(INDEX(InvoiceDetails[],SMALL(IF(InvoiceDetails[Invoice '#]=rngInvoice,ROW(InvoiceDetails[])-ROW(InvoiceDetails[#Headers])), ROW(10:10)), MATCH($C$10, InvoiceDetails[#Headers], 0)),"")} -> INV-2302-034 | D18: {=IFERROR(INDEX(InvoiceDetails[],SMALL(IF(InvoiceDetails[Invoice '#]=rngInvoice,ROW(InvoiceDetails[])-ROW(InvoiceDetails[#Headers])), ROW(10:10)), MATCH($D$10, InvoiceDetails[#Headers], 0)),"")} -> 924 | E18: {=IFERROR(INDEX(InvoiceDetails[],SMALL(IF(InvoiceDetails[Invoice '#]=rngInvoice,ROW(InvoiceDetails[])-ROW(InvoiceDetails[#Headers])), ROW(10:10)), MATCH($E$10, InvoiceDetails[#Headers], 0)),"")} -> 29 | F18: {=IFERROR(INDEX(InvoiceDetails[],SMALL(IF(InvoiceDetails[Invoice '#]=rngInvoice,ROW(InvoiceDetails[])-ROW(InvoiceDetails[#Headers])), ROW(10:10)), MATCH($F$10, InvoiceDetails[#Headers], 0)),"")} -> 3 | G18: =IFERROR((D18*E18)-F18,"") -> 26793
B19: {=IFERROR(INDEX(InvoiceDetails[],SMALL(IF(InvoiceDetails[Invoice '#]=rngInvoice,ROW(InvoiceDetails[])-ROW(InvoiceDetails[#Headers])), ROW(11:11)), MATCH($B$10, InvoiceDetails[#Headers], 0)),"")} -> PC-IND-XL39M-09 | C19: {=IFERROR(INDEX(InvoiceDetails[],SMALL(IF(InvoiceDetails[Invoice '#]=rngInvoice,ROW(InvoiceDetails[])-ROW(InvoiceDetails[#Headers])), ROW(11:11)), MATCH($C$10, InvoiceDetails[#Headers], 0)),"")} -> INV-2302-035 | D19: {=IFERROR(INDEX(InvoiceDetails[],SMALL(IF(InvoiceDetails[Invoice '#]=rngInvoice,ROW(InvoiceDetails[])-ROW(InvoiceDetails[#Headers])), ROW(11:11)), MATCH($D$10, InvoiceDetails[#Headers], 0)),"")} -> 716 | E19: {=IFERROR(INDEX(InvoiceDetails[],SMALL(IF(InvoiceDetails[Invoice '#]=rngInvoice,ROW(InvoiceDetails[])-ROW(InvoiceDetails[#Headers])), ROW(11:11)), MATCH($E$10, InvoiceDetails[#Headers], 0)),"")} -> 30 | F19: {=IFERROR(INDEX(InvoiceDetails[],SMALL(IF(InvoiceDetails[Invoice '#]=rngInvoice,ROW(InvoiceDetails[])-ROW(InvoiceDetails[#Headers])), ROW(11:11)), MATCH($F$10, InvoiceDetails[#Headers], 0)),"")} -> 0 | G19: =IFERROR((D19*E19)-F19,"") -> 21480
B20: {=IFERROR(INDEX(InvoiceDetails[],SMALL(IF(InvoiceDetails[Invoice '#]=rngInvoice,ROW(InvoiceDetails[])-ROW(InvoiceDetails[#Headers])), ROW(12:12)), MATCH($B$10, InvoiceDetails[#Headers], 0)),"")} -> ED-IND-WI83S-42 | C20: {=IFERROR(INDEX(InvoiceDetails[],SMALL(IF(InvoiceDetails[Invoice '#]=rngInvoice,ROW(InvoiceDetails[])-ROW(InvoiceDetails[#Headers])), ROW(12:12)), MATCH($C$10, InvoiceDetails[#Headers], 0)),"")} -> INV-2302-036 | D20: {=IFERROR(INDEX(InvoiceDetails[],SMALL(IF(InvoiceDetails[Invoice '#]=rngInvoice,ROW(InvoiceDetails[])-ROW(InvoiceDetails[#Headers])), ROW(12:12)), MATCH($D$10, InvoiceDetails[#Headers], 0)),"")} -> 820 | E20: {=IFERROR(INDEX(InvoiceDetails[],SMALL(IF(InvoiceDetails[Invoice '#]=rngInvoice,ROW(InvoiceDetails[])-ROW(InvoiceDetails[#Headers])), ROW(12:12)), MATCH($E$10, InvoiceDetails[#Headers], 0)),"")} -> 28 | F20: {=IFERROR(INDEX(InvoiceDetails[],SMALL(IF(InvoiceDetails[Invoice '#]=rngInvoice,ROW(InvoiceDetails[])-ROW(InvoiceDetails[#Headers])), ROW(12:12)), MATCH($F$10, InvoiceDetails[#Headers], 0)),"")} -> 0 | G20: =IFERROR((D20*E20)-F20,"") -> 22960
B21: {=IFERROR(INDEX(InvoiceDetails[],SMALL(IF(InvoiceDetails[Invoice '#]=rngInvoice,ROW(InvoiceDetails[])-ROW(InvoiceDetails[#Headers])), ROW(13:13)), MATCH($B$10, InvoiceDetails[#Headers], 0)),"")} -> ED-IND-ZU15L-03 | C21: {=IFERROR(INDEX(InvoiceDetails[],SMALL(IF(InvoiceDetails[Invoice '#]=rngInvoice,ROW(InvoiceDetails[])-ROW(InvoiceDetails[#Headers])), ROW(13:13)), MATCH($C$10, InvoiceDetails[#Headers], 0)),"")} -> INV-2302-037 | D21: {=IFERROR(INDEX(InvoiceDetails[],SMALL(IF(InvoiceDetails[Invoice '#]=rngInvoice,ROW(InvoiceDetails[])-ROW(InvoiceDetails[#Headers])), ROW(13:13)), MATCH($D$10, InvoiceDetails[#Headers], 0)),"")} -> 993 | E21: {=IFERROR(INDEX(InvoiceDetails[],SMALL(IF(InvoiceDetails[Invoice '#]=rngInvoice,ROW(InvoiceDetails[])-ROW(InvoiceDetails[#Headers])), ROW(13:13)), MATCH($E$10, InvoiceDetails[#Headers], 0)),"")} -> 31 | F21: {=IFERROR(INDEX(InvoiceDetails[],SMALL(IF(InvoiceDetails[Invoice '#]=rngInvoice,ROW(InvoiceDetails[])-ROW(InvoiceDetails[#Headers])), ROW(13:13)), MATCH($F$10, InvoiceDetails[#Headers], 0)),"")} -> 0 | G21: =IFERROR((D21*E21)-F21,"") -> 30783
B22: {=IFERROR(INDEX(InvoiceDetails[],SMALL(IF(InvoiceDetails[Invoice '#]=rngInvoice,ROW(InvoiceDetails[])-ROW(InvoiceDetails[#Headers])), ROW(14:14)), MATCH($B$10, InvoiceDetails[#Headers], 0)),"")} | C22: {=IFERROR(INDEX(InvoiceDetails[],SMALL(IF(InvoiceDetails[Invoice '#]=rngInvoice,ROW(InvoiceDetails[])-ROW(InvoiceDetails[#Headers])), ROW(14:14)), MATCH($C$10, InvoiceDetails[#Headers], 0)),"")} | D22: {=IFERROR(INDEX(InvoiceDetails[],SMALL(IF(InvoiceDetails[Invoice '#]=rngInvoice,ROW(InvoiceDetails[])-ROW(InvoiceDetails[#Headers])), ROW(14:14)), MATCH($D$10, InvoiceDetails[#Headers], 0)),"")} | E22: {=IFERROR(INDEX(InvoiceDetails[],SMALL(IF(InvoiceDetails[Invoice '#]=rngInvoice,ROW(InvoiceDetails[])-ROW(InvoiceDetails[#Headers])), ROW(14:14)), MATCH($E$10, InvoiceDetails[#Headers], 0)),"")} | F22: {=IFERROR(INDEX(InvoiceDetails[],SMALL(IF(InvoiceDetails[Invoice '#]=rngInvoice,ROW(InvoiceDetails[])-ROW(InvoiceDetails[#Headers])), ROW(14:14)), MATCH($F$10, InvoiceDetails[#Headers], 0)),"")} | G22: =IFERROR((D22*E22)-F22,"")
B23: {=IFERROR(INDEX(InvoiceDetails[],SMALL(IF(InvoiceDetails[Invoice '#]=rngInvoice,ROW(InvoiceDetails[])-ROW(InvoiceDetails[#Headers])), ROW(15:15)), MATCH($B$10, InvoiceDetails[#Headers], 0)),"")} | C23: {=IFERROR(INDEX(InvoiceDetails[],SMALL(IF(InvoiceDetails[Invoice '#]=rngInvoice,ROW(InvoiceDetails[])-ROW(InvoiceDetails[#Headers])), ROW(15:15)), MATCH($C$10, InvoiceDetails[#Headers], 0)),"")} | D23: {=IFERROR(INDEX(InvoiceDetails[],SMALL(IF(InvoiceDetails[Invoice '#]=rngInvoice,ROW(InvoiceDetails[])-ROW(InvoiceDetails[#Headers])), ROW(15:15)), MATCH($D$10, InvoiceDetails[#Headers], 0)),"")} | E23: {=IFERROR(INDEX(InvoiceDetails[],SMALL(IF(InvoiceDetails[Invoice '#]=rngInvoice,ROW(InvoiceDetails[])-ROW(InvoiceDetails[#Headers])), ROW(15:15)), MATCH($E$10, InvoiceDetails[#Headers], 0)),"")} | F23: {=IFERROR(INDEX(InvoiceDetails[],SMALL(IF(InvoiceDetails[Invoice '#]=rngInvoice,ROW(InvoiceDetails[])-ROW(InvoiceDetails[#Headers])), ROW(15:15)), MATCH($F$10, InvoiceDetails[#Headers], 0)),"")} | G23: =IFERROR((D23*E23)-F23,"")
B24: {=IFERROR(INDEX(InvoiceDetails[],SMALL(IF(InvoiceDetails[Invoice '#]=rngInvoice,ROW(InvoiceDetails[])-ROW(InvoiceDetails[#Headers])), ROW(16:16)), MATCH($B$10, InvoiceDetails[#Headers], 0)),"")} | C24: {=IFERROR(INDEX(InvoiceDetails[],SMALL(IF(InvoiceDetails[Invoice '#]=rngInvoice,ROW(InvoiceDetails[])-ROW(InvoiceDetails[#Headers])), ROW(16:16)), MATCH($C$10, InvoiceDetails[#Headers], 0)),"")} | D24: {=IFERROR(INDEX(InvoiceDetails[],SMALL(IF(InvoiceDetails[Invoice '#]=rngInvoice,ROW(InvoiceDetails[])-ROW(InvoiceDetails[#Headers])), ROW(16:16)), MATCH($D$10, InvoiceDetails[#Headers], 0)),"")} | E24: {=IFERROR(INDEX(InvoiceDetails[],SMALL(IF(InvoiceDetails[Invoice '#]=rngInvoice,ROW(InvoiceDetails[])-ROW(InvoiceDetails[#Headers])), ROW(16:16)), MATCH($E$10, InvoiceDetails[#Headers], 0)),"")} | F24: {=IFERROR(INDEX(InvoiceDetails[],SMALL(IF(InvoiceDetails[Invoice '#]=rngInvoice,ROW(InvoiceDetails[])-ROW(InvoiceDetails[#Headers])), ROW(16:16)), MATCH($F$10, InvoiceDetails[#Headers], 0)),"")} | G24: =IFERROR((D24*E24)-F24,"")
B25: {=IFERROR(INDEX(InvoiceDetails[],SMALL(IF(InvoiceDetails[Invoice '#]=rngInvoice,ROW(InvoiceDetails[])-ROW(InvoiceDetails[#Headers])), ROW(27:27)), MATCH($B$10, InvoiceDetails[#Headers], 0)),"")} | C25: {=IFERROR(INDEX(InvoiceDetails[],SMALL(IF(InvoiceDetails[Invoice '#]=rngInvoice,ROW(InvoiceDetails[])-ROW(InvoiceDetails[#Headers])), ROW(27:27)), MATCH($C$10, InvoiceDetails[#Headers], 0)),"")} | D25: {=IFERROR(INDEX(InvoiceDetails[],SMALL(IF(InvoiceDetails[Invoice '#]=rngInvoice,ROW(InvoiceDetails[])-ROW(InvoiceDetails[#Headers])), ROW(27:27)), MATCH($D$10, InvoiceDetails[#Headers], 0)),"")} | E25: {=IFERROR(INDEX(InvoiceDetails[],SMALL(IF(InvoiceDetails[Invoice '#]=rngInvoice,ROW(InvoiceDetails[])-ROW(InvoiceDetails[#Headers])), ROW(27:27)), MATCH($E$10, InvoiceDetails[#Headers], 0)),"")} | F25: {=IFERROR(INDEX(InvoiceDetails[],SMALL(IF(InvoiceDetails[Invoice '#]=rngInvoice,ROW(InvoiceDetails[])-ROW(InvoiceDetails[#Headers])), ROW(27:27)), MATCH($F$10, InvoiceDetails[#Headers], 0)),"")} | G25: =IFERROR((D25*E25)-F25,"")
F26: Invoice Subtotal | G26: =SUM(ProjectInvoice[Price]) -> 251714
F27: Tax Rate | G27: =VLOOKUP(rngInvoice,#REF!,5) -> #REF!
F28: Sales Tax | G28: =G26*G27 -> #REF!
F29: Other | G29: =VLOOKUP(rngInvoice,#REF!,6) -> #REF!
B30: ="Make all checks payable to "&CompanyName&"." -> Make all checks payable to Kumar Coaters. | F30: Deposit Received | G30: =VLOOKUP(rngInvoice,#REF!,7) -> #REF!
B31: Total due in 30 days. Overdue accounts subject to a service charge of 5% per month. | F31: TOTAL | G31: =(G26+G28+G29)-G30 -> #REF!

Sheet Invoice details
B1: Invoice Details
B3: Description | C3: Invoice # | D3: Item # | E3: Qty | F3: Unit price | G3: Discount | H3: Total
B4: ='Sales Data'!C3 -> INV-2301-001 | C4: 3-456-1 | D4: ='Sales Data'!E3 -> ED-IND-BF94R-96 | E4: ='Sales Data'!G3 -> 925 | F4: ='Sales Data'!H3 -> 28 | G4: 1 | H4: =(InvoiceDetails[[#This Row],[Qty]]*InvoiceDetails[[#This Row],[Unit price]])-InvoiceDetails[[#This Row],[Discount]] -> 25899
B5: ='Sales Data'!C4 -> INV-2301-002 | C5: 3-456-2 | D5: ='Sales Data'!E4 -> PC-IND-ES58E-77 | E5: ='Sales Data'!G4 -> 717 | F5: ='Sales Data'!H4 -> 30 | G5: 2 | H5: =(InvoiceDetails[[#This Row],[Qty]]*InvoiceDetails[[#This Row],[Unit price]])-InvoiceDetails[[#This Row],[Discount]] -> 21508
B6: ='Sales Data'!C5 -> INV-2301-003 | C6: 3-456-1 | D6: ='Sales Data'!E5 -> ED-IND-PW28Y-87 | E6: ='Sales Data'!G5 -> 502 | F6: ='Sales Data'!H5 -> 26 | G6: 3 | H6: =(InvoiceDetails[[#This Row],[Qty]]*InvoiceDetails[[#This Row],[Unit price]])-InvoiceDetails[[#This Row],[Discount]] -> 13049
B7: ='Sales Data'!C6 -> INV-2301-004 | C7: 3-456-1 | D7: ='Sales Data'!E6 -> ED-IND-FH42M-31 | E7: ='Sales Data'!G6 -> 914 | F7: ='Sales Data'!H6 -> 25 | G7: 4 | H7: =(InvoiceDetails[[#This Row],[Qty]]*InvoiceDetails[[#This Row],[Unit price]])-InvoiceDetails[[#This Row],[Discount]] -> 22846
B8: ='Sales Data'!C7 -> INV-2301-005 | C8: 3-456-1 | D8: ='Sales Data'!E7 -> ED-IND-DG79M-42 | E8: ='Sales Data'!G7 -> 542 | F8: ='Sales Data'!H7 -> 25 | G8: 5 | H8: =(InvoiceDetails[[#This Row],[Qty]]*InvoiceDetails[[#This Row],[Unit price]])-InvoiceDetails[[#This Row],[Discount]] -> 13545
B9: ='Sales Data'!C8 -> INV-2301-006 | C9: 3-456-1 | D9: ='Sales Data'!E8 -> ED-IND-UE60O-04 | E9: ='Sales Data'!G8 -> 854 | F9: ='Sales Data'!H8 -> 23 | G9: 6 | H9: =(InvoiceDetails[[#This Row],[Qty]]*InvoiceDetails[[#This Row],[Unit price]])-InvoiceDetails[[#This Row],[Discount]] -> 19636
B10: ='Sales Data'!C9 -> INV-2301-007 | C10: 3-456-1 | D10: ='Sales Data'!E9 -> ED-IND-LN87Z-82 | E10: ='Sales Data'!G9 -> 677 | F10: ='Sales Data'!H9 -> 24 | G10: 7 | H10: =(InvoiceDetails[[#This Row],[Qty]]*InvoiceDetails[[#This Row],[Unit price]])-InvoiceDetails[[#This Row],[Discount]] -> 16241
B11: ='Sales Data'!C10 -> INV-2301-008 | C11: 3-456-1 | D11: ='Sales Data'!E10 -> ED-IND-FF18D-36 | E11: ='Sales Data'!G10 -> 706 | F11: ='Sales Data'!H10 -> 26 | G11: 8 | H11: =(InvoiceDetails[[#This Row],[Qty]]*InvoiceDetails[[#This Row],[Unit price]])-InvoiceDetails[[#This Row],[Discount]] -> 18348
B12: ='Sales Data'!C11 -> INV-2301-009 | C12: 3-456-1 | D12: ='Sales Data'!E11 -> ED-IND-MV42W-01 | E12: ='Sales Data'!G11 -> 877 | F12: ='Sales Data'!H11 -> 26 | G12: 9 | H12: =(InvoiceDetails[[#This Row],[Qty]]*InvoiceDetails[[#This Row],[Unit price]])-InvoiceDetails[[#This Row],[Discount]] -> 22793
B13: ='Sales Data'!C12 -> INV-2301-010 | C13: 3-456-1 | D13: ='Sales Data'!E12 -> ED-IND-NU37O-73 | E13: ='Sales Data'!G12 -> 635 | F13: ='Sales Data'!H12 -> 22 | G13: 10 | H13: =(InvoiceDetails[[#This Row],[Qty]]*InvoiceDetails[[#This Row],[Unit price]])-InvoiceDetails[[#This Row],[Discount]] -> 13960
B14: ='Sales Data'!C13 -> INV-2301-011 | C14: 3-456-1 | D14: ='Sales Data'!E13 -> ED-IND-XH20D-48 | E14: ='Sales Data'!G13 -> 809 | F14: ='Sales Data'!H13 -> 31 | G14: 11 | H14: =(InvoiceDetails[[#This Row],[Qty]]*InvoiceDetails[[#This Row],[Unit price]])-InvoiceDetails[[#This Row],[Discount]] -> 25068
B15: ='Sales Data'!C14 -> INV-2301-012 | C15: 3-456-1 | D15: ='Sales Data'!E14 -> PC-IND-QG66C-31 | E15: ='Sales Data'!G14 -> 994 | F15: ='Sales Data'!H14 -> 27 | G15: 12 | H15: =(InvoiceDetails[[#This Row],[Qty]]*InvoiceDetails[[#This Row],[Unit price]])-InvoiceDetails[[#This Row],[Discount]] -> 26826
... B28: ='Sales Data'!C27 -> INV-2301-025 | C28: 3-456-1 | D28: ='Sales Data'!E27 -> ED-IND-JV82I-92 | E28: ='Sales Data'!G27 -> 892 | F28: ='Sales Data'!H27 -> 25 | G28: 25 | H28: =(InvoiceDetails[[#This Row],[Qty]]*InvoiceDetails[[#This Row],[Unit price]])-InvoiceDetails[[#This Row],[Discount]] -> 22275
B29: ='Sales Data'!C28 -> INV-2301-026 | C29: 3-456-2 | D29: ='Sales Data'!E28 -> PC-IND-GB95C-85 | E29: ='Sales Data'!G28 -> 585 | F29: ='Sales Data'!H28 -> 24 | H29: =(InvoiceDetails[[#This Row],[Qty]]*InvoiceDetails[[#This Row],[Unit price]])-InvoiceDetails[[#This Row],[Discount]] -> 14040
B30: ='Sales Data'!C29 -> INV-2301-027 | C30: 3-456-2 | D30: ='Sales Data'!E29 -> ED-IND-XN73Y-21 | E30: ='Sales Data'!G29 -> 511 | F30: ='Sales Data'!H29 -> 21 | G30: 5 | H30: =(InvoiceDetails[[#This Row],[Qty]]*InvoiceDetails[[#This Row],[Unit price]])-InvoiceDetails[[#This Row],[Discount]] -> 10726
B31: ='Sales Data'!C30 -> INV-2301-028 | C31: 3-456-2 | D31: ='Sales Data'!E30 -> ED-IND-BU40X-81 | E31: ='Sales Data'!G30 -> 800 | F31: ='Sales Data'!H30 -> 31 | G31: 7 | H31: =(InvoiceDetails[[#This Row],[Qty]]*InvoiceDetails[[#This Row],[Unit price]])-InvoiceDetails[[#This Row],[Discount]] -> 24793
B32: ='Sales Data'!C31 -> INV-2302-029 | C32: 3-456-2 | D32: ='Sales Data'!E31 -> ED-IND-TV20R-31 | E32: ='Sales Data'!G31 -> 994 | F32: ='Sales Data'!H31 -> 21 | H32: =(InvoiceDetails[[#This Row],[Qty]]*InvoiceDetails[[#This Row],[Unit price]])-InvoiceDetails[[#This Row],[Discount]] -> 20874
B33: ='Sales Data'!C32 -> INV-2302-030 | C33: 3-456-2 | D33: ='Sales Data'!E32 -> ED-IND-UU36L-66 | E33: ='Sales Data'!G32 -> 533 | F33: ='Sales Data'!H32 -> 26 | H33: =(InvoiceDetails[[#This Row],[Qty]]*InvoiceDetails[[#This Row],[Unit price]])-InvoiceDetails[[#This Row],[Discount]] -> 13858
B34: ='Sales Data'!C33 -> INV-2302-031 | C34: 3-456-2 | D34: ='Sales Data'!E33 -> ED-IND-FE78W-05 | E34: ='Sales Data'!G33 -> 998 | F34: ='Sales Data'!H33 -> 29 | H34: =(InvoiceDetails[[#This Row],[Qty]]*InvoiceDetails[[#This Row],[Unit price]])-InvoiceDetails[[#This Row],[Discount]] -> 28942
B35: ='Sales Data'!C34 -> INV-2302-032 | C35: 3-456-2 | D35: ='Sales Data'!E34 -> ED-IND-KQ16R-25 | E35: ='Sales Data'!G34 -> 851 | F35: ='Sales Data'!H34 -> 24 | H35: =(InvoiceDetails[[#This Row],[Qty]]*InvoiceDetails[[#This Row],[Unit price]])-InvoiceDetails[[#This Row],[Discount]] -> 20424
B36: ='Sales Data'!C35 -> INV-2302-033 | C36: 3-456-2 | D36: ='Sales Data'!E35 -> ED-IND-JK94K-77 | E36: ='Sales Data'!G35 -> 919 | F36: ='Sales Data'!H35 -> 21 | H36: =(InvoiceDetails[[#This Row],[Qty]]*InvoiceDetails[[#This Row],[Unit price]])-InvoiceDetails[[#This Row],[Discount]] -> 19299
B37: ='Sales Data'!C36 -> INV-2302-034 | C37: 3-456-2 | D37: ='Sales Data'!E36 -> ED-IND-CR92V-20 | E37: ='Sales Data'!G36 -> 924 | F37: ='Sales Data'!H36 -> 29 | G37: 3 | H37: =(InvoiceDetails[[#This Row],[Qty]]*InvoiceDetails[[#This Row],[Unit price]])-InvoiceDetails[[#This Row],[Discount]] -> 26793
B38: ='Sales Data'!C37 -> INV-2302-035 | C38: 3-456-2 | D38: ='Sales Data'!E37 -> PC-IND-XL39M-09 | E38: ='Sales Data'!G37 -> 716 | F38: ='Sales Data'!H37 -> 30 | H38: =(InvoiceDetails[[#This Row],[Qty]]*InvoiceDetails[[#This Row],[Unit price]])-InvoiceDetails[[#This Row],[Discount]] -> 21480
B39: ='Sales Data'!C38 -> INV-2302-036 | C39: 3-456-2 | D39: ='Sales Data'!E38 -> ED-IND-WI83S-42 | E39: ='Sales Data'!G38 -> 820 | F39: ='Sales Data'!H38 -> 28 | H39: =(InvoiceDetails[[#This Row],[Qty]]*InvoiceDetails[[#This Row],[Unit price]])-InvoiceDetails[[#This Row],[Discount]] -> 22960
B40: ='Sales Data'!C39 -> INV-2302-037 | C40: 3-456-2 | D40: ='Sales Data'!E39 -> ED-IND-ZU15L-03 | E40: ='Sales Data'!G39 -> 993 | F40: ='Sales Data'!H39 -> 31 | H40: =(InvoiceDetails[[#This Row],[Qty]]*InvoiceDetails[[#This Row],[Unit price]])-InvoiceDetails[[#This Row],[Discount]] -> 30783
B41: ='Sales Data'!C40 -> INV-2302-038 | D41: ='Sales Data'!E40 -> ED-IND-WW79U-71 | E41: ='Sales Data'!G40 -> 857 | F41: ='Sales Data'!H40 -> 25 | H41: =(InvoiceDetails[[#This Row],[Qty]]*InvoiceDetails[[#This Row],[Unit price]])-InvoiceDetails[[#This Row],[Discount]] -> 21425
B42: ='Sales Data'!C41 -> INV-2302-039 | D42: ='Sales Data'!E41 -> ED-IND-ID66P-47 | E42: ='Sales Data'!G41 -> 643 | F42: ='Sales Data'!H41 -> 28 | H42: =(InvoiceDetails[[#This Row],[Qty]]*InvoiceDetails[[#This Row],[Unit price]])-InvoiceDetails[[#This Row],[Discount]] -> 18004
B43: ='Sales Data'!C42 -> INV-2302-040 | D43: ='Sales Data'!E42 -> ED-IND-IZ39P-50 | E43: ='Sales Data'!G42 -> 548 | F43: ='Sales Data'!H42 -> 28 | H43: =(InvoiceDetails[[#This Row],[Qty]]*InvoiceDetails[[#This Row],[Unit price]])-InvoiceDetails[[#This Row],[Discount]] -> 15344
B44: ='Sales Data'!C43 -> INV-2302-041 | D44: ='Sales Data'!E43 -> ED-IND-ZD11V-50 | E44: ='Sales Data'!G43 -> 602 | F44: ='Sales Data'!H43 -> 21 | H44: =(InvoiceDetails[[#This Row],[Qty]]*InvoiceDetails[[#This Row],[Unit price]])-InvoiceDetails[[#This Row],[Discount]] -> 12642
B45: ='Sales Data'!C44 -> INV-2302-042 | D45: ='Sales Data'!E44 -> ED-IND-CA47Q-81 | E45: ='Sales Data'!G44 -> 717 | F45: ='Sales Data'!H44 -> 28 | H45: =(InvoiceDetails[[#This Row],[Qty]]*InvoiceDetails[[#This Row],[Unit price]])-InvoiceDetails[[#This Row],[Discount]] -> 20076
B46: ='Sales Data'!C45 -> INV-2302-043 | D46: ='Sales Data'!E45 -> ED-IND-NI30Z-49 | E46: ='Sales Data'!G45 -> 551 | F46: ='Sales Data'!H45 -> 23 | H46: =(InvoiceDetails[[#This Row],[Qty]]*InvoiceDetails[[#This Row],[Unit price]])-InvoiceDetails[[#This Row],[Discount]] -> 12673
B47: ='Sales Data'!C46 -> INV-2302-044 | D47: ='Sales Data'!E46 -> PC-IND-VT75H-21 | E47: ='Sales Data'!G46 -> 951 | F47: ='Sales Data'!H46 -> 22 | H47: =(InvoiceDetails[[#This Row],[Qty]]*InvoiceDetails[[#This Row],[Unit price]])-InvoiceDetails[[#This Row],[Discount]] -> 20922
B48: ='Sales Data'!C47 -> INV-2302-045 | D48: ='Sales Data'!E47 -> ED-IND-MS12H-50 | E48: ='Sales Data'!G47 -> 812 | F48: ='Sales Data'!H47 -> 28 | H48: =(InvoiceDetails[[#This Row],[Qty]]*InvoiceDetails[[#This Row],[Unit price]])-InvoiceDetails[[#This Row],[Discount]] -> 22736
B49: ='Sales Data'!C48 -> INV-2302-046 | D49: ='Sales Data'!E48 -> ED-IND-QK22X-55 | E49: ='Sales Data'!G48 -> 839 | F49: ='Sales Data'!H48 -> 22 | H49: =(InvoiceDetails[[#This Row],[Qty]]*InvoiceDetails[[#This Row],[Unit price]])-InvoiceDetails[[#This Row],[Discount]] -> 18458
B50: ='Sales Data'!C49 -> INV-2302-047 | D50: ='Sales Data'!E49 -> PC-IND-CL12F-19 | E50: ='Sales Data'!G49 -> 586 | F50: ='Sales Data'!H49 -> 25 | H50: =(InvoiceDetails[[#This Row],[Qty]]*InvoiceDetails[[#This Row],[Unit price]])-InvoiceDetails[[#This Row],[Discount]] -> 14650
B51: ='Sales Data'!C50 -> INV-2302-048 | D51: ='Sales Data'!E50 -> PC-IND-NP93B-18 | E51: ='Sales Data'!G50 -> 562 | F51: ='Sales Data'!H50 -> 28 | H51: =(InvoiceDetails[[#This Row],[Qty]]*InvoiceDetails[[#This Row],[Unit price]])-InvoiceDetails[[#This Row],[Discount]] -> 15736
B52: ='Sales Data'!C51 -> INV-2302-049 | D52: ='Sales Data'!E51 -> PC-IND-IR21R-23 | E52: ='Sales Data'!G51 -> 623 | F52: ='Sales Data'!H51 -> 26 | H52: =(InvoiceDetails[[#This Row],[Qty]]*InvoiceDetails[[#This Row],[Unit price]])-InvoiceDetails[[#This Row],[Discount]] -> 16198
... B821: ='Sales Data'!C820 -> INV-2503-818 | D821: ='Sales Data'!E820 -> ED-IND-KJ88Q-86 | E821: ='Sales Data'!G820 -> 919 | F821: ='Sales Data'!H820 -> 21 | H821: =(InvoiceDetails[[#This Row],[Qty]]*InvoiceDetails[[#This Row],[Unit price]])-InvoiceDetails[[#This Row],[Discount]] -> 19299

Sheet Monthly Data pivot
A1: Sum of Total | B1: Column Labels
B2: Jan | C2: Feb | D2: Mar | E2: Apr | F2: May | G2: Jun | H2: Jul | I2: Aug | J2: Sep | K2: Oct | L2: Nov | M2: Dec | N2: Grand Total
A3: Row Labels
A4: ED coating | B4: 336055 | C4: 466304 | D4: 375298 | E4: 460784 | F4: 505848 | G4: 479313 | H4: 500106 | I4: 347214 | J4: 155252 | K4: 162460 | L4: 202306 | M4: 138474 | N4: 4129414
A5: 2024 | B5: 336055 | C5: 466304 | D5: 375298 | E5: 460784 | F5: 505848 | G5: 479313 | H5: 500106 | I5: 347214 | J5: 155252 | K5: 162460 | L5: 202306 | M5: 138474 | N5: 4129414
A6: Powder Coating | B6: 260077 | C6: 79233 | D6: 208213 | E6: 131768 | F6: 129394 | G6: 118769 | H6: 93668 | I6: 186210 | J6: 29556 | K6: 138082 | L6: 66989 | M6: 64735 | N6: 1506694
A7: 2024 | B7: 260077 | C7: 79233 | D7: 208213 | E7: 131768 | F7: 129394 | G7: 118769 | H7: 93668 | I7: 186210 | J7: 29556 | K7: 138082 | L7: 66989 | M7: 64735 | N7: 1506694
A8: Grand Total | B8: 596132 | C8: 545537 | D8: 583511 | E8: 592552 | F8: 635242 | G8: 598082 | H8: 593774 | I8: 533424 | J8: 184808 | K8: 300542 | L8: 269295 | M8: 203209 | N8: 5636108

Sheet Sheet2
A1: Sum of Total | B1: Column Labels
A2: Row Labels | B2: 2025 | C2: Grand Total
A3: ED coating | B3: 1412417 | C3: 1412417
A4: Powder Coating | B4: 395583 | C4: 395583
A5: Grand Total | B5: 1808000 | C5: 1808000

Sheet Sales Data
B2: Date | C2: Invoice Number | D2: Customer | E2: Part Number | F2: Service | G2: Quantity | H2: Unit Price | I2: Total | J2: Sales Person | K2: Region
B3: 44930 | C3: INV-2301-001 | D3: 123456789 | E3: ED-IND-BF94R-96 | F3: ED coating | G3: 925 | H3: 28 | I3: 25900 | J3: 123456789 | K3: Pune
B4: 44931 | C4: INV-2301-002 | D4: 123456790 | E4: PC-IND-ES58E-77 | F4: Powder Coating | G4: 717 | H4: 30 | I4: 21510 | J4: 123456789 | K4: Mumbai
B5: 44932 | C5: INV-2301-003 | D5: 123456791 | E5: ED-IND-PW28Y-87 | F5: ED coating | G5: 502 | H5: 26 | I5: 13052 | J5: 123456789 | K5: Pune
B6: 44933 | C6: INV-2301-004 | D6: 123456792 | E6: ED-IND-FH42M-31 | F6: ED coating | G6: 914 | H6: 25 | I6: 22850 | J6: 123456789 | K6: Mumbai
B7: 44934 | C7: INV-2301-005 | D7: 123456793 | E7: ED-IND-DG79M-42 | F7: ED coating | G7: 542 | H7: 25 | I7: 13550 | J7: 123456789 | K7: Mumbai
B8: 44935 | C8: INV-2301-006 | D8: 123456794 | E8: ED-IND-UE60O-04 | F8: ED coating | G8: 854 | H8: 23 | I8: 19642 | J8: 123456789 | K8: Pune
B9: 44936 | C9: INV-2301-007 | D9: 123456795 | E9: ED-IND-LN87Z-82 | F9: ED coating | G9: 677 | H9: 24 | I9: 16248 | J9: 123456789 | K9: Pune
B10: 44937 | C10: INV-2301-008 | D10: 123456796 | E10: ED-IND-FF18D-36 | F10: ED coating | G10: 706 | H10: 26 | I10: 18356 | J10: 123456789 | K10: Pune
B11: 44938 | C11: INV-2301-009 | D11: 123456797 | E11: ED-IND-MV42W-01 | F11: ED coating | G11: 877 | H11: 26 | I11: 22802 | J11: 123456789 | K11: Pune
B12: 44939 | C12: INV-2301-010 | D12: 123456798 | E12: ED-IND-NU37O-73 | F12: ED coating | G12: 635 | H12: 22 | I12: 13970 | J12: 123456789 | K12: Mumbai
B13: 44940 | C13: INV-2301-011 | D13: 123456799 | E13: ED-IND-XH20D-48 | F13: ED coating | G13: 809 | H13: 31 | I13: 25079 | J13: 123456789 | K13: Pune
B14: 44941 | C14: INV-2301-012 | D14: 123456800 | E14: PC-IND-QG66C-31 | F14: Powder Coating | G14: 994 | H14: 27 | I14: 26838 | J14: 123456789 | K14: Mumbai
... B639: 45566 | C639: INV-2410-637 | D639: 123457425 | E639: ED-IND-ZF18V-17 | F639: ED coating | G639: 226 | H639: 25 | I639: 5650 | J639: 123456789 | K639: Pune
B640: 45567 | C640: INV-2410-638 | D640: 123457426 | E640: ED-IND-OZ76J-01 | F640: ED coating | G640: =RANDBETWEEN(250, 510) -> 508 | H640: 31 | I640: 8711 | J640: 123456789 | K640: Pune
B641: 45568 | C641: INV-2410-639 | D641: 123457427 | E641: PC-IND-ZH64L-21 | F641: Powder Coating | G641: =RANDBETWEEN(250, 510) -> 430 | H641: 26 | I641: 9360 | J641: 123456789 | K641: Pune
B642: 45569 | C642: INV-2410-640 | D642: 123457428 | E642: ED-IND-XF13Q-10 | F642: ED coating | G642: =RANDBETWEEN(250, 510) -> 453 | H642: 30 | I642: 9120 | J642: 123456789 | K642: Pune
B643: 45570 | C643: INV-2410-641 | D643: 123457429 | E643: ED-IND-BM20C-78 | F643: ED coating | G643: =RANDBETWEEN(250, 510) -> 494 | H643: 30 | I643: 7800 | J643: 123456789 | K643: Pune
B644: 45571 | C644: INV-2410-642 | D644: 123457430 | E644: PC-IND-EP27E-20 | F644: Powder Coating | G644: =RANDBETWEEN(250, 510) -> 423 | H644: 28 | I644: 8960 | J644: 123456789 | K644: Pune
B645: 45572 | C645: INV-2410-643 | D645: 123457431 | E645: ED-IND-FV18L-32 | F645: ED coating | G645: =RANDBETWEEN(250, 510) -> 388 | H645: 26 | I645: 11258 | J645: 123456789 | K645: Pune
B646: 45573 | C646: INV-2410-644 | D646: 123457432 | E646: PC-IND-IC10Z-85 | F646: Powder Coating | G646: =RANDBETWEEN(250, 510) -> 303 | H646: 28 | I646: 12908 | J646: 123456789 | K646: Pune
B647: 45574 | C647: INV-2410-645 | D647: 123457433 | E647: ED-IND-ZK46V-70 | F647: ED coating | G647: =RANDBETWEEN(250, 510) -> 447 | H647: 31 | I647: 8463 | J647: 123456789 | K647: Pune
B648: 45575 | C648: INV-2410-646 | D648: 123457434 | E648: ED-IND-LB73Y-47 | F648: ED coating | G648: =RANDBETWEEN(250, 510) -> 335 | H648: 21 | I648: 10122 | J648: 123456789 | K648: Pune
B649: 45576 | C649: INV-2410-647 | D649: 123457435 | E649: PC-IND-ZZ90Z-21 | F649: Powder Coating | G649: =RANDBETWEEN(250, 510) -> 396 | H649: 21 | I649: 10101 | J649: 123456789 | K649: Mumbai
B650: 45577 | C650: INV-2410-648 | D650: 123457436 | E650: ED-IND-YY93P-18 | F650: ED coating | G650: =RANDBETWEEN(250, 510) -> 492 | H650: 29 | I650: 12905 | J650: 123456789 | K650: Mumbai
B651: 45578 | C651: INV-2410-649 | D651: 123457437 | E651: ED-IND-RU51P-79 | F651: ED coating | G651: =RANDBETWEEN(250, 510) -> 278 | H651: 25 | I651: 7950 | J651: 123456789 | K651: Mumbai
... B692: 45619 | C692: INV-2411-690 | D692: 123457478 | E692: ED-IND-GP88P-45 | F692: ED coating | G692: =RANDBETWEEN(250, 510) -> 428 | H692: 22 | I692: 10406 | J692: 123456789 | K692: Mumbai
B693: 45620 | C693: INV-2411-691 | D693: 123457479 | E693: PC-IND-HE71K-95 | F693: Powder Coating | G693: 274 | H693: 28 | I693: 7672 | J693: 123456789 | K693: Pune
B694: 45621 | C694: INV-2411-692 | D694: 123457480 | E694: PC-IND-FT52J-47 | F694: Powder Coating | G694: 297 | H694: 26 | I694: 7722 | J694: 123456789 | K694: Pune
B695: 45622 | C695: INV-2411-693 | D695: 123457481 | E695: ED-IND-QQ25V-20 | F695: ED coating | G695: 294 | H695: 28 | I695: 8232 | J695: 123456789 | K695: Mumbai
B696: 45623 | C696: INV-2411-694 | D696: 123457482 | E696: ED-IND-SN84C-96 | F696: ED coating | G696: 250 | H696: 25 | I696: 6250 | J696: 123456789 | K696: Pune
B697: 45624 | C697: INV-2411-695 | D697: 123457483 | E697: ED-IND-YT77I-52 | F697: ED coating | G697: 255 | H697: 28 | I697: 7140 | J697: 123456789 | K697: Pune
B698: 45625 | C698: INV-2411-696 | D698: 123457484 | E698: PC-IND-MG84Z-91 | F698: Powder Coating | G698: 251 | H698: 26 | I698: 6526 | J698: 123456789 | K698: Pune
B699: 45626 | C699: INV-2411-697 | D699: 123457485 | E699: PC-IND-TE50N-54 | F699: Powder Coating | G699: 293 | H699: 21 | I699: 6153 | J699: 123456789 | K699: Pune
B700: 45627 | C700: INV-2412-698 | D700: 123457486 | E700: PC-IND-UU74B-15 | F700: Powder Coating | G700: 232 | H700: 21 | I700: 4872 | J700: 123456789 | K700: Mumbai
B701: 45628 | C701: INV-2412-699 | D701: 123457487 | E701: ED-IND-CP44L-46 | F701: ED coating | G701: 231 | H701: 26 | I701: 6006 | J701: 123456789 | K701: Mumbai
B702: 45629 | C702: INV-2412-700 | D702: 123457488 | E702: ED-IND-BA53J-37 | F702: ED coating | G702: 218 | H702: 21 | I702: 4578 | J702: 123456789 | K702: Pune
B703: 45630 | C703: INV-2412-701 | D703: 123457489 | E703: ED-IND-QD21W-53 | F703: ED coating | G703: 277 | H703: 31 | I703: 8587 | J703: 123456789 | K703: Mumbai
B704: 45631 | C704: INV-2412-702 | D704: 123457490 | E704: ED-IND-CR97J-08 | F704: ED coating | G704: 234 | H704: 30 | I704: 7020 | J704: 123456789 | K704: Pune
... B820: 45747 | C820: INV-2503-818 | D820: 123457606 | E820: ED-IND-KJ88Q-86 | F820: ED coating | G820: 919 | H820: 21 | I820: 19299 | J820: 123456789 | K820: Mumbai

Sheet Sheet1
A1: Date | B1: Invoice Number | C1: Customer | D1: Part Number | E1: Service | F1: Quantity | G1: Unit Price | H1: Total | I1: Sales Person | J1: Region
A2: 44930 | B2: INV-2301-001 | C2: 123456789 | D2: ED-IND-BF94R-96 | E2: ED coating | F2: 925 | G2: 28 | H2: 25900 | I2: 123456789 | J2: Pune
A3: 44931 | B3: INV-2301-002 | C3: 123456790 | D3: PC-IND-ES58E-77 | E3: Powder Coating | F3: 717 | G3: 30 | H3: 21510 | I3: 123456789 | J3: Mumbai
A4: 44932 | B4: INV-2301-003 | C4: 123456791 | D4: ED-IND-PW28Y-87 | E4: ED coating | F4: 502 | G4: 26 | H4: 13052 | I4: 123456789 | J4: Pune
A5: 44933 | B5: INV-2301-004 | C5: 123456792 | D5: ED-IND-FH42M-31 | E5: ED coating | F5: 914 | G5: 25 | H5: 22850 | I5: 123456789 | J5: Mumbai
A6: 44934 | B6: INV-2301-005 | C6: 123456793 | D6: ED-IND-DG79M-42 | E6: ED coating | F6: 542 | G6: 25 | H6: 13550 | I6: 123456789 | J6: Mumbai
A7: 44935 | B7: INV-2301-006 | C7: 123456794 | D7: ED-IND-UE60O-04 | E7: ED coating | F7: 854 | G7: 23 | H7: 19642 | I7: 123456789 | J7: Pune
A8: 44936 | B8: INV-2301-007 | C8: 123456795 | D8: ED-IND-LN87Z-82 | E8: ED coating | F8: 677 | G8: 24 | H8: 16248 | I8: 123456789 | J8: Pune
A9: 44937 | B9: INV-2301-008 | C9: 123456796 | D9: ED-IND-FF18D-36 | E9: ED coating | F9: 706 | G9: 26 | H9: 18356 | I9: 123456789 | J9: Pune
A10: 44938 | B10: INV-2301-009 | C10: 123456797 | D10: ED-IND-MV42W-01 | E10: ED coating | F10: 877 | G10: 26 | H10: 22802 | I10: 123456789 | J10: Pune
A11: 44939 | B11: INV-2301-010 | C11: 123456798 | D11: ED-IND-NU37O-73 | E11: ED coating | F11: 635 | G11: 22 | H11: 13970 | I11: 123456789 | J11: Mumbai
A12: 44940 | B12: INV-2301-011 | C12: 123456799 | D12: ED-IND-XH20D-48 | E12: ED coating | F12: 809 | G12: 31 | H12: 25079 | I12: 123456789 | J12: Pune
A13: 44941 | B13: INV-2301-012 | C13: 123456800 | D13: PC-IND-QG66C-31 | E13: Powder Coating | F13: 994 | G13: 27 | H13: 26838 | I13: 123456789 | J13: Mumbai
... A638: 45566 | B638: INV-2410-637 | C638: 123457425 | D638: ED-IND-ZF18V-17 | E638: ED coating | F638: 226 | G638: 25 | H638: 5650 | I638: 123456789 | J638: Pune
A639: 45567 | B639: INV-2410-638 | C639: 123457426 | D639: ED-IND-OZ76J-01 | E639: ED coating | F639: =RANDBETWEEN(250, 510) -> 287 | G639: 31 | H639: 8711 | I639: 123456789 | J639: Pune
A640: 45568 | B640: INV-2410-639 | C640: 123457427 | D640: PC-IND-ZH64L-21 | E640: Powder Coating | F640: =RANDBETWEEN(250, 510) -> 256 | G640: 26 | H640: 9360 | I640: 123456789 | J640: Pune
A641: 45569 | B641: INV-2410-640 | C641: 123457428 | D641: ED-IND-XF13Q-10 | E641: ED coating | F641: =RANDBETWEEN(250, 510) -> 332 | G641: 30 | H641: 9120 | I641: 123456789 | J641: Pune
A642: 45570 | B642: INV-2410-641 | C642: 123457429 | D642: ED-IND-BM20C-78 | E642: ED coating | F642: =RANDBETWEEN(250, 510) -> 440 | G642: 30 | H642: 7800 | I642: 123456789 | J642: Pune
A643: 45571 | B643: INV-2410-642 | C643: 123457430 | D643: PC-IND-EP27E-20 | E643: Powder Coating | F643: =RANDBETWEEN(250, 510) -> 471 | G643: 28 | H643: 8960 | I643: 123456789 | J643: Pune
A644: 45572 | B644: INV-2410-643 | C644: 123457431 | D644: ED-IND-FV18L-32 | E644: ED coating | F644: =RANDBETWEEN(250, 510) -> 283 | G644: 26 | H644: 11258 | I644: 123456789 | J644: Pune
A645: 45573 | B645: INV-2410-644 | C645: 123457432 | D645: PC-IND-IC10Z-85 | E645: Powder Coating | F645: =RANDBETWEEN(250, 510) -> 371 | G645: 28 | H645: 12908 | I645: 123456789 | J645: Pune
A646: 45574 | B646: INV-2410-645 | C646: 123457433 | D646: ED-IND-ZK46V-70 | E646: ED coating | F646: =RANDBETWEEN(250, 510) -> 468 | G646: 31 | H646: 8463 | I646: 123456789 | J646: Pune
A647: 45575 | B647: INV-2410-646 | C647: 123457434 | D647: ED-IND-LB73Y-47 | E647: ED coating | F647: =RANDBETWEEN(250, 510) -> 295 | G647: 21 | H647: 10122 | I647: 123456789 | J647: Pune
A648: 45576 | B648: INV-2410-647 | C648: 123457435 | D648: PC-IND-ZZ90Z-21 | E648: Powder Coating | F648: =RANDBETWEEN(250, 510) -> 400 | G648: 21 | H648: 10101 | I648: 123456789 | J648: Mumbai
A649: 45577 | B649: INV-2410-648 | C649: 123457436 | D649: ED-IND-YY93P-18 | E649: ED coating | F649: =RANDBETWEEN(250, 510) -> 303 | G649: 29 | H649: 12905 | I649: 123456789 | J649: Mumbai
A650: 45578 | B650: INV-2410-649 | C650: 123457437 | D650: ED-IND-RU51P-79 | E650: ED coating | F650: =RANDBETWEEN(250, 510) -> 489 | G650: 25 | H650: 7950 | I650: 123456789 | J650: Mumbai
... A691: 45619 | B691: INV-2411-690 | C691: 123457478 | D691: ED-IND-GP88P-45 | E691: ED coating | F691: =RANDBETWEEN(250, 510) -> 419 | G691: 22 | H691: 10406 | I691: 123456789 | J691: Mumbai
A692: 45620 | B692: INV-2411-691 | C692: 123457479 | D692: PC-IND-HE71K-95 | E692: Powder Coating | F692: 274 | G692: 28 | H692: 7672 | I692: 123456789 | J692: Pune
A693: 45621 | B693: INV-2411-692 | C693: 123457480 | D693: PC-IND-FT52J-47 | E693: Powder Coating | F693: 297 | G693: 26 | H693: 7722 | I693: 123456789 | J693: Pune
A694: 45622 | B694: INV-2411-693 | C694: 123457481 | D694: ED-IND-QQ25V-20 | E694: ED coating | F694: 294 | G694: 28 | H694: 8232 | I694: 123456789 | J694: Mumbai
A695: 45623 | B695: INV-2411-694 | C695: 123457482 | D695: ED-IND-SN84C-96 | E695: ED coating | F695: 250 | G695: 25 | H695: 6250 | I695: 123456789 | J695: Pune
A696: 45624 | B696: INV-2411-695 | C696: 123457483 | D696: ED-IND-YT77I-52 | E696: ED coating | F696: 255 | G696: 28 | H696: 7140 | I696: 123456789 | J696: Pune
A697: 45625 | B697: INV-2411-696 | C697: 123457484 | D697: PC-IND-MG84Z-91 | E697: Powder Coating | F697: 251 | G697: 26 | H697: 6526 | I697: 123456789 | J697: Pune
A698: 45626 | B698: INV-2411-697 | C698: 123457485 | D698: PC-IND-TE50N-54 | E698: Powder Coating | F698: 293 | G698: 21 | H698: 6153 | I698: 123456789 | J698: Pune
A699: 45627 | B699: INV-2412-698 | C699: 123457486 | D699: PC-IND-UU74B-15 | E699: Powder Coating | F699: 232 | G699: 21 | H699: 4872 | I699: 123456789 | J699: Mumbai
A700: 45628 | B700: INV-2412-699 | C700: 123457487 | D700: ED-IND-CP44L-46 | E700: ED coating | F700: 231 | G700: 26 | H700: 6006 | I700: 123456789 | J700: Mumbai
A701: 45629 | B701: INV-2412-700 | C701: 123457488 | D701: ED-IND-BA53J-37 | E701: ED coating | F701: 218 | G701: 21 | H701: 4578 | I701: 123456789 | J701: Pune
A702: 45630 | B702: INV-2412-701 | C702: 123457489 | D702: ED-IND-QD21W-53 | E702: ED coating | F702: 277 | G702: 31 | H702: 8587 | I702: 123456789 | J702: Mumbai
A703: 45631 | B703: INV-2412-702 | C703: 123457490 | D703: ED-IND-CR97J-08 | E703: ED coating | F703: 234 | G703: 30 | H703: 7020 | I703: 123456789 | J703: Pune
... A819: 45747 | B819: INV-2503-818 | C819: 123457606 | D819: ED-IND-KJ88Q-86 | E819: ED coating | F819: 919 | G819: 21 | H819: 19299 | I819: 123456789 | J819: Mumbai

Sheet GPT cache
VZV138820: {"hash":"22021e4335577cd12061edc6d701bf91bc6384ea2ada1adb256ca17c8143cad4","version":1,"value":"[[\"Scoop Up Happiness!\"]]"}
PFZ927018: {"hash":"f55e2529706a6af54911d249ab4f572f705b852b083ee19899e20ae18804410d","version":1,"value":"[[\"=IF(ISNUMBER(SEARCH(\\\"ED\\\", E1)), \\\"ED\\\", \\\"PC\\\")\"]]"}
